humancompatible/__init__.py
humancompatible-0.0.0.dist-info/LICENSE
humancompatible-0.0.0.dist-info/METADATA
humancompatible-0.0.0.dist-info/WHEEL
humancompatible-0.0.0.dist-info/RECORD
