Metadata-Version: 2.1
Name: humancompatible
Version: 0.0.0
Summary: 
License: Apache-2.0
Requires-Python: >=3.8,<3.11
Classifier: License :: OSI Approved :: Apache Software License
Classifier: Programming Language :: Python :: 3
Classifier: Programming Language :: Python :: 3.8
Classifier: Programming Language :: Python :: 3.9
Classifier: Programming Language :: Python :: 3.10
